povm_toolbox/__init__.py
povm_toolbox/utilities.py
povm_toolbox/library/__init__.py
povm_toolbox/library/classical_shadows.py
povm_toolbox/library/dilation_measurement.py
povm_toolbox/library/locally_biased_classical_shadows.py
povm_toolbox/library/mutually_unbiased_bases_measurements.py
povm_toolbox/library/povm_implementation.py
povm_toolbox/library/randomized_projective_measurements.py
povm_toolbox/library/metadata/__init__.py
povm_toolbox/library/metadata/povm_metadata.py
povm_toolbox/library/metadata/rpm_metadata.py
povm_toolbox/post_processor/__init__.py
povm_toolbox/post_processor/dual_from_empirical_frequencies.py
povm_toolbox/post_processor/dual_from_marginal_probabilities.py
povm_toolbox/post_processor/dual_from_state.py
povm_toolbox/post_processor/median_of_means.py
povm_toolbox/post_processor/povm_post_processor.py
povm_toolbox/quantum_info/__init__.py
povm_toolbox/quantum_info/multi_qubit_dual.py
povm_toolbox/quantum_info/multi_qubit_frame.py
povm_toolbox/quantum_info/multi_qubit_povm.py
povm_toolbox/quantum_info/product_dual.py
povm_toolbox/quantum_info/product_frame.py
povm_toolbox/quantum_info/product_povm.py
povm_toolbox/quantum_info/single_qubit_povm.py
povm_toolbox/quantum_info/base/__init__.py
povm_toolbox/quantum_info/base/base_dual.py
povm_toolbox/quantum_info/base/base_frame.py
povm_toolbox/quantum_info/base/base_povm.py
povm_toolbox/sampler/__init__.py
povm_toolbox/sampler/povm_pub_result.py
povm_toolbox/sampler/povm_sampler.py
povm_toolbox/sampler/povm_sampler_job.py
povm_toolbox/sampler/povm_sampler_pub.py
povm_toolbox-0.2.0.dist-info/METADATA
povm_toolbox-0.2.0.dist-info/WHEEL
povm_toolbox-0.2.0.dist-info/licenses/LICENSE.txt
povm_toolbox-0.2.0.dist-info/RECORD
